{
    "status": 0,
    "result": {
        "location": {
            "lng": 114.02597365999998,
            "lat": 22.546053549705483
        },
        "formatted_address": "广东省深圳市福田区农轩路55号",
        "business": "香蜜湖,竹子林",
        "addressComponent": {
            "country": "中国",
            "country_code": 0,
            "province": "广东省",
            "city": "深圳市",
            "district": "福田区",
            "adcode": "440304",
            "street": "农轩路",
            "street_number": "55号",
            "direction": "西",
            "distance": "60"
        },
        "pois": [],
        "roads": [],
        "poiRegions": [
            {
                "direction_desc": "内",
                "name": "彩虹阁",
                "tag": "房地产"
            }
        ],
        "sematic_description": "彩虹阁内",
        "cityCode": 340
    }
}